timew_subtag/__init__.py
timew_subtag-0.1.0.dist-info/entry_points.txt
timew_subtag-0.1.0.dist-info/WHEEL
timew_subtag-0.1.0.dist-info/METADATA
timew_subtag-0.1.0.dist-info/RECORD
