Metadata-Version: 2.1
Name: timew-subtag
Version: 0.1.0
Summary: 
Author: Hayk Khachatryan
Author-email: hi@hayk.io
Requires-Python: >=3.8,<4.0
Classifier: Programming Language :: Python :: 3
Classifier: Programming Language :: Python :: 3.10
Classifier: Programming Language :: Python :: 3.8
Classifier: Programming Language :: Python :: 3.9
Requires-Dist: arrow (>=1.1.1,<2.0.0)
Requires-Dist: click (>=8.0.1,<9.0.0)
Requires-Dist: rich (>=10.9.0,<11.0.0)
Requires-Dist: timew (>=0.0.22,<0.0.23)
